epivizFileParser/BamFile.py
epivizFileParser/BaseFile.py
epivizFileParser/BigBed.py
epivizFileParser/BigWig.py
epivizFileParser/GWASBigBedPIP.py
epivizFileParser/GWASBigBedPval.py
epivizFileParser/GtfFile.py
epivizFileParser/GtfParsedFile.py
epivizFileParser/GtfTabixFile.py
epivizFileParser/HDF5File.py
epivizFileParser/Helper.py
epivizFileParser/InteractionBigBed.py
epivizFileParser/S3HDF5File.py
epivizFileParser/SamFile.py
epivizFileParser/SplicingBamFile.py
epivizFileParser/TbxFile.py
epivizFileParser/TileDB.py
epivizFileParser/TileDBTbxFile.py
epivizFileParser/TranscriptTbxFile.py
epivizFileParser/__init__.py
epivizFileParser/utils.py
epivizFileParser-0.0.4.dist-info/AUTHORS.rst
epivizFileParser-0.0.4.dist-info/LICENSE.txt
epivizFileParser-0.0.4.dist-info/METADATA
epivizFileParser-0.0.4.dist-info/WHEEL
epivizFileParser-0.0.4.dist-info/top_level.txt
epivizFileParser-0.0.4.dist-info/RECORD
