Metadata-Version: 2.1
Name: epivizFileParser
Version: 0.0.4
Summary: Parse and Query Genomic File Formats.
Home-page: https://github.com/epiviz/epivizFileParser
Author: jkanche
Author-email: jayaram.kancherla@gmail.com
License: mit
Project-URL: Documentation, https://efsFileParser.readthedocs.io
Platform: any
Classifier: Development Status :: 4 - Beta
Classifier: Programming Language :: Python
License-File: LICENSE.txt
License-File: AUTHORS.rst
Requires-Dist: numpy
Requires-Dist: scipy
Requires-Dist: aiocache
Requires-Dist: pandas
Requires-Dist: requests
Requires-Dist: pysam
Requires-Dist: h5py
Requires-Dist: ujson
Requires-Dist: docopt
Requires-Dist: tqdm
Requires-Dist: tiledb
Requires-Dist: boto3
Requires-Dist: botocore
Requires-Dist: importlib-metadata ; python_version < "3.8"
Provides-Extra: testing
Requires-Dist: pytest ; extra == 'testing'
Requires-Dist: pytest-cov ; extra == 'testing'
